lumpur/__init__.py
lumpur/fit/__init__.py
lumpur/fit/interpolation/__init__.py
lumpur/fit/interpolation/linear.py
lumpur/mlx/__init__.py
lumpur/num/__init__.py
lumpur/num/polynomial.py
lumpur/sim/__init__.py
lumpur/sim/grid/__init__.py
lumpur/sim/grid/utils.py
lumpur/sim/grid/walls.py
lumpur/use/__init__.py
lumpur/use/forces/__init__.py
lumpur/use/forces/drag.py
lumpur/use/forces/electric.py
lumpur/use/forces/gravitational.py
lumpur/use/forces/gravitational2.py
lumpur/use/forces/magnetic.py
lumpur/use/forces/normal.py
lumpur/use/forces/normal2.py
lumpur/use/forces/spring.py
lumpur/use/forces/spring2.py
lumpur/use/misc/__init__.py
lumpur/use/misc/info.py
lumpur/use/shapes/__init__.py
lumpur/use/shapes/rectangle.py
lumpur/use/shapes/triangle.py
lumpur/use/utils/__init__.py
lumpur/use/utils/color2.py
lumpur/use/vectors/__init__.py
lumpur/use/vectors/vect2.py
lumpur/use/vectors/vect3.py
lumpur/viz/__init__.py
lumpur/viz/anim/__init__.py
lumpur/viz/plot/__init__.py
lumpur/viz/plot/binary.py
lumpur/viz/plot/polynomial.py
lumpur-0.0.6.dist-info/LICENSE
lumpur-0.0.6.dist-info/METADATA
lumpur-0.0.6.dist-info/WHEEL
lumpur-0.0.6.dist-info/top_level.txt
lumpur-0.0.6.dist-info/RECORD
