Metadata-Version: 2.1
Name: lumpur
Version: 0.0.6
Summary: learn to use methods for processing unclear response
Home-page: https://github.com/dudung/lumpur
Author: Sparisoma Viridi
Author-email: dudung@gmail.com
License: MIT
Classifier: Programming Language :: Python :: 3
Classifier: License :: OSI Approved :: MIT License
Classifier: Operating System :: OS Independent
Requires-Python: >=3.12
License-File: LICENSE
Requires-Dist: numpy>=1.26.4
Requires-Dist: matplotlib>=3.8.4
Requires-Dist: pandas>=2.2.2
